__init__.py
assignmenttree.py
cli.py
cookie_transport.py
devilry-examiner.py
examinercmd.py
exampleclient.py
ez_setup.py
models.py
setup.py
tests.py
devilry_xmlrpc_client.egg-info/PKG-INFO
devilry_xmlrpc_client.egg-info/SOURCES.txt
devilry_xmlrpc_client.egg-info/dependency_links.txt
devilry_xmlrpc_client.egg-info/top_level.txt