Metadata-Version: 1.0
Name: devilry-xmlrpc-client
Version: 0.1.1
Summary: The devilry xmlrpc client and shell scripts.
Home-page: http://devilry.github.com
Author: Espen Angell Kristiansen
Author-email: espeak@ifi.uio.no
License: UNKNOWN
Platform: UNKNOWN
